Metadata-Version: 1.0
Name: uamobile
Version: 0.2.14
Summary: WSGIUserAgentMobile - mobile user agent string parser for WSGI applications
Home-page: http://code.google.com/p/wsgiuseragentmobile/
Author: Chihiro Sakatoku
Author-email: csakatoku@gmail.com
License: MIT License
Platform: any
Classifier: Development Status :: 4 - Beta
Classifier: License :: OSI Approved :: MIT License
Classifier: Programming Language :: Python
Classifier: Operating System :: OS Independent
Classifier: Topic :: Software Development :: Libraries :: Python Modules
Classifier: Topic :: Internet :: WWW/HTTP :: WSGI :: Middleware
